mcp_eregistrations_bpa/__init__.py
mcp_eregistrations_bpa/__main__.py
mcp_eregistrations_bpa/config.py
mcp_eregistrations_bpa/exceptions.py
mcp_eregistrations_bpa/py.typed
mcp_eregistrations_bpa/server.py
mcp_eregistrations_bpa/arazzo/__init__.py
mcp_eregistrations_bpa/arazzo/expression.py
mcp_eregistrations_bpa/audit/__init__.py
mcp_eregistrations_bpa/audit/context.py
mcp_eregistrations_bpa/audit/logger.py
mcp_eregistrations_bpa/audit/models.py
mcp_eregistrations_bpa/auth/__init__.py
mcp_eregistrations_bpa/auth/callback.py
mcp_eregistrations_bpa/auth/cas.py
mcp_eregistrations_bpa/auth/oidc.py
mcp_eregistrations_bpa/auth/permissions.py
mcp_eregistrations_bpa/auth/token_manager.py
mcp_eregistrations_bpa/bpa_client/__init__.py
mcp_eregistrations_bpa/bpa_client/client.py
mcp_eregistrations_bpa/bpa_client/endpoints.py
mcp_eregistrations_bpa/bpa_client/errors.py
mcp_eregistrations_bpa/bpa_client/models.py
mcp_eregistrations_bpa/db/__init__.py
mcp_eregistrations_bpa/db/connection.py
mcp_eregistrations_bpa/db/migrations.py
mcp_eregistrations_bpa/rollback/__init__.py
mcp_eregistrations_bpa/rollback/manager.py
mcp_eregistrations_bpa/tools/__init__.py
mcp_eregistrations_bpa/tools/actions.py
mcp_eregistrations_bpa/tools/analysis.py
mcp_eregistrations_bpa/tools/audit.py
mcp_eregistrations_bpa/tools/behaviours.py
mcp_eregistrations_bpa/tools/bots.py
mcp_eregistrations_bpa/tools/classifications.py
mcp_eregistrations_bpa/tools/costs.py
mcp_eregistrations_bpa/tools/debug_strategies.py
mcp_eregistrations_bpa/tools/debugger.py
mcp_eregistrations_bpa/tools/determinants.py
mcp_eregistrations_bpa/tools/document_requirements.py
mcp_eregistrations_bpa/tools/export.py
mcp_eregistrations_bpa/tools/external_services.py
mcp_eregistrations_bpa/tools/fields.py
mcp_eregistrations_bpa/tools/form_errors.py
mcp_eregistrations_bpa/tools/formio_helpers.py
mcp_eregistrations_bpa/tools/forms.py
mcp_eregistrations_bpa/tools/jsonlogic_builder.py
mcp_eregistrations_bpa/tools/large_response.py
mcp_eregistrations_bpa-0.12.2.dist-info/METADATA
mcp_eregistrations_bpa-0.12.2.dist-info/WHEEL
mcp_eregistrations_bpa-0.12.2.dist-info/entry_points.txt
mcp_eregistrations_bpa-0.12.2.dist-info/licenses/LICENSE
mcp_eregistrations_bpa-0.12.2.dist-info/RECORD
