Metadata-Version: 2.4
Name: mcp-eregistrations-bpa
Version: 0.12.2
Summary: MCP server for eRegistrations BPA platform
Project-URL: Homepage, https://github.com/UNCTAD-eRegistrations/mcp-eregistrations-bpa
Project-URL: Repository, https://github.com/UNCTAD-eRegistrations/mcp-eregistrations-bpa
Project-URL: Documentation, https://github.com/UNCTAD-eRegistrations/mcp-eregistrations-bpa#readme
Author-email: Moulay Mehdi Benmoumen <benmoumen@gmail.com>
Maintainer: UNCTAD Business Facilitation Section
License: Proprietary - UNCTAD/DIAE/Business Facilitation Section
License-File: LICENSE
Keywords: ai,bpa,claude,eregistrations,govtech,mcp,unctad
Classifier: Development Status :: 4 - Beta
Classifier: Intended Audience :: Developers
Classifier: License :: Other/Proprietary License
Classifier: Programming Language :: Python :: 3
Classifier: Programming Language :: Python :: 3.11
Classifier: Programming Language :: Python :: 3.12
Classifier: Programming Language :: Python :: 3.13
Classifier: Topic :: Office/Business :: Groupware
Classifier: Topic :: Software Development :: Libraries :: Python Modules
Requires-Python: >=3.11
Requires-Dist: aiosqlite>=0.22.1
Requires-Dist: authlib
Requires-Dist: fastmcp>=2.11.3
Requires-Dist: httpx
Requires-Dist: pydantic>=2.0
Requires-Dist: pyyaml
